OmnicommSun/__init__.py
OmnicommSun/omincomm_sun.py
omnisun-0.0.1.dist-info/METADATA
omnisun-0.0.1.dist-info/WHEEL
omnisun-0.0.1.dist-info/top_level.txt
omnisun-0.0.1.dist-info/RECORD
